munggae_cloud/Embed.py
munggae_cloud/__init__.py
munggae_cloud/bot.py
munggae_cloud/db.py
munggae_cloud/logging.py
munggae_cloud/utils.py
munggae_cloud/watcher.py
munggae_cloud-0.0.3.dist-info/METADATA
munggae_cloud-0.0.3.dist-info/WHEEL
munggae_cloud-0.0.3.dist-info/RECORD
