Metadata-Version: 2.4
Name: Munggae-Cloud
Version: 0.0.3
Summary: py-cord를 활용한 래퍼 라이브러리 입니다
Project-URL: Homepage, https://github.hyomuel.com
Author-email: 효무엘 <help@hyomuel.com>
License: MIT
Keywords: api,bot,discord,discord-bot,discord-py,easy-bot,munggae,py-cord,wrapper
Requires-Python: >=3.10
Requires-Dist: py-cord[voice]>=2.7.0
